{
  "name": "aggregate-account",
  "description": "Account aggregation with relation to party",
  "targets": "parquet",
  "entities": [
    {
      "name": "account-id",
      "description": "Unique account identificator",
      "type": "string"
    },
    {
      "name": "party-id",
      "description": "Party identificator",
      "type": "string"
    }
  ],
  "features": [
    {
      "name": "type",
      "description": "Type of party account (saving account, current account, etc.)",
      "type": "int"
    },
    {
      "name": "open-date",
      "description": "Account opening date",
      "type": "timestamp"
    },
    {
      "name": "state",
      "description": "Account state (e.g. active, closed, etc.)",
      "type": "int"
    },
    {
      "name": "record-date",
      "description": "The date when the record was created",
      "type": "timestamp"
    }
  ]
}